geotime_classify/__init__.py
geotime_classify/geotime_classify.py
geotime_classify/geotime_classify_backup.py
geotime_classify/geotime_schema.py
geotime_classify/datasets/Fake_data.csv
geotime_classify/datasets/LSTM_RNN_Geotime_Classify_v_0.07.pth
geotime_classify/datasets/LSTM_RNN_Geotime_Classify_v_0.07_dict.pth
geotime_classify/datasets/NA_states_provinces.csv
geotime_classify/datasets/Test_1.csv
geotime_classify/datasets/Test_2_kaggle.csv
geotime_classify/datasets/Test_4_kaggle.csv
geotime_classify/datasets/__init__.py
geotime_classify/datasets/city.csv
geotime_classify/datasets/continent_code.csv
geotime_classify/datasets/country.csv
geotime_classify/datasets/country_lookup.csv
geotime_classify/datasets/county_cc_c_number.csv
geotime_classify/models/LSTM_RNN_Geotime_Classify_v_0.07.pth
geotime_classify/models/LSTM_RNN_Geotime_Classify_v_0.07_dict.pth
geotime_classify/models/LSTM_RNN_Geotime_Classify_v_0.08_dict.pth
geotime_classify/models/LSTM_RNN_Geotime_Classify_v_0.09_dict.pth
geotime_classify/models/LSTM_RNN_Geotime_Classify_v_0.10_dict.pth
geotime_classify/models/LSTM_RNN_Geotime_Classify_v_0.11_dict.pth
geotime_classify/models/LSTM_RNN_Geotime_Classify_v_0.12_dict.pth
geotime_classify/models/__init__.py
tests/__init__.py
tests/test_geotimeclassify.py
geotime_classify-0.8.2.dist-info/AUTHORS.rst
geotime_classify-0.8.2.dist-info/LICENSE
geotime_classify-0.8.2.dist-info/METADATA
geotime_classify-0.8.2.dist-info/WHEEL
geotime_classify-0.8.2.dist-info/top_level.txt
geotime_classify-0.8.2.dist-info/RECORD
