Metadata-Version: 2.1
Name: geotime-classify
Version: 0.8.2
Summary: Categorizes spatial and temporal columns for csv files. Standardizes date columns for transformations
Home-page: https://github.com/jataware/geotime_classify
Author: Kyle Marsh
Author-email: kyle@jataware.com
License: LGPL-3.0-or-later
Project-URL: Changelog, https://github.com/jataware/geotime_classify/blob/master/CHANGELOG.md
Project-URL: Issue Tracker, https://github.com/jataware/geotime_classify/issues
Keywords: LSTM,RNN,Classification,Date,Datetime,Coordinates,Latitude,Longitude
Platform: UNKNOWN
Classifier: Development Status :: 5 - Production/Stable
Classifier: Intended Audience :: Developers
Classifier: License :: OSI Approved :: GNU Lesser General Public License v3 or later (LGPLv3+)
Classifier: Operating System :: Unix
Classifier: Operating System :: POSIX
Classifier: Operating System :: POSIX :: Linux
Classifier: Programming Language :: Python
Classifier: Programming Language :: Python :: 3.8
Classifier: Programming Language :: Python :: 3.9
Classifier: Programming Language :: Python :: Implementation :: PyPy
Classifier: Topic :: Utilities
Requires-Python: >=3.6
Requires-Dist: bump2version (==1.0.1)
Requires-Dist: arrow (==1.0.3)
Requires-Dist: fuzzywuzzy (==0.18.0)
Requires-Dist: numpy (>=1.22)
Requires-Dist: scipy (==1.6.2)
Requires-Dist: pandas (==1.2.3)
Requires-Dist: joblib (==1.0.1)
Requires-Dist: torch (==1.8.1)
Requires-Dist: torchvision (==0.9.1)
Requires-Dist: pydantic (==1.8.2)
Requires-Dist: python-Levenshtein (==0.12.2)
Provides-Extra: dev
Requires-Dist: pytest (>=3.7) ; extra == 'dev'
Requires-Dist: twine (>=3.3.0) ; extra == 'dev'
